omniformer/__init__.py
omniformer/config.py
omniformer/model.py
omniformer/utils.py
omniformer-0.1.1.dist-info/METADATA
omniformer-0.1.1.dist-info/WHEEL
omniformer-0.1.1.dist-info/entry_points.txt
omniformer-0.1.1.dist-info/top_level.txt
omniformer-0.1.1.dist-info/RECORD
